dronedirector
