Metadata-Version: 1.2
Name: dronedirector
Version: 0.0.7
Summary: A simple Python package for simulating aerial drones
Home-page: https://github.com/avmarchenko/dronedirector
Author: Alex Marchenko
Author-email: alexvmarch@gmail.com
Maintainer-email: alexvmarch@gmail.com
License: Apache License Version 2.0
Download-URL: https://github.com/avmarchenko/dronedirector/archive/v0.0.7.tar.gz
Platform: UNKNOWN
